count_split/__init__.py
count_split/count_split.py
count_split-0.0.99.dist-info/METADATA
count_split-0.0.99.dist-info/WHEEL
count_split-0.0.99.dist-info/top_level.txt
count_split-0.0.99.dist-info/RECORD
