Metadata-Version: 2.1
Name: count-split
Version: 0.0.99
Summary: Count splitting for random sampled count matrices
Home-page: https://scottyler892@bitbucket.org/scottyler892/count_split
Author: Scott Tyler
Author-email: scottyler89@gmail.com
License: UNKNOWN
Platform: UNKNOWN
Classifier: Programming Language :: Python :: 3
Classifier: License :: OSI Approved :: GNU Affero General Public License v3
Classifier: Operating System :: OS Independent
Requires-Dist: h5py
Requires-Dist: numpy
Requires-Dist: scipy
Requires-Dist: numba
